mdviewer/__init__.py
mdviewer/app.py
mdviewer/cli.py
mdviewer/search/__init__.py
mdviewer/search/fd_search.py
mdviewer/search/rg_search.py
mdviewer/static/script.js
mdviewer/static/style.css
mdviewer/templates/index.html
mdviewer/templates/search.html
mdviewer/templates/viewer.html
mdviewer-0.2.3.dist-info/licenses/LICENSE
mdviewer-0.2.3.dist-info/METADATA
mdviewer-0.2.3.dist-info/WHEEL
mdviewer-0.2.3.dist-info/entry_points.txt
mdviewer-0.2.3.dist-info/top_level.txt
mdviewer-0.2.3.dist-info/RECORD
