Metadata-Version: 2.4
Name: mdviewer
Version: 0.2.3
Summary: GitHub-style Markdown viewer
Author-email: Biao Jiang <github@minsignal.com>
License: MIT
Project-URL: Homepage, https://github.com/biaojiang/mdviewer
Project-URL: Documentation, https://github.com/biaojiang/mdviewer#readme
Project-URL: Source, https://github.com/biaojiang/mdviewer
Project-URL: Issues, https://github.com/biaojiang/mdviewer/issues
Keywords: markdown,cli,viewer,html
Classifier: License :: OSI Approved :: MIT License
Classifier: Programming Language :: Python :: 3
Classifier: Topic :: Utilities
Classifier: Environment :: Console
Classifier: Operating System :: OS Independent
Classifier: Natural Language :: English
Requires-Python: >=3.8
License-File: LICENSE
Requires-Dist: flask
Requires-Dist: livereload
Requires-Dist: markdown-it-py
Requires-Dist: beautifulsoup4
Dynamic: license-file
